gwa_spotify_api/__init__.py
gwa_spotify_api/exceptions.py
gwa_spotify_api/spotify_api.py
gwa_spotify_api/spotify_auth_api.py
gwa_spotify_api-0.0.9.data/data/data/spotify-token.pickle
gwa_spotify_api-0.0.9.dist-info/DESCRIPTION.rst
gwa_spotify_api-0.0.9.dist-info/METADATA
gwa_spotify_api-0.0.9.dist-info/RECORD
gwa_spotify_api-0.0.9.dist-info/WHEEL
gwa_spotify_api-0.0.9.dist-info/metadata.json
gwa_spotify_api-0.0.9.dist-info/top_level.txt
