Metadata-Version: 2.0
Name: gwa-spotify-api
Version: 0.0.9
Summary: wrapper for spotify web api
Home-page: https://github.com/goodwordalchemy/spotify-api
Author: David Goldberg
Author-email: goodwordalchemy@gmail.com
License: MIT
Keywords: spotify api wrapper
Platform: UNKNOWN
Classifier: Development Status :: 4 - Beta
Classifier: Intended Audience :: Developers
Classifier: License :: OSI Approved :: MIT License
Classifier: Programming Language :: Python :: 3
Requires-Python: >=3
Requires-Dist: rauth
